{
  "title": "1.1.2 UML 101",
  "start_page": 34,
  "end_page": 36,
  "indent_level": 1,
  "hierarchy": [
    "Data-Oriented Programming (node0)",
    "Part1—Flexibility (node1)",
    "1 Complexity of object-oriented programming (node2)",
    "Chapter 1"
  ],
  "extraction_time": "2025-08-06T19:46:39.254863",
  "content_length": 4690,
  "file_path": "/home/nadle/projects/Knowledge_Sherpa/v2/TOC_Normalization/TOC_Structure/extracted_sections_with_pages/Data-Oriented_Programming_(node0)/Part1—Flexibility_(node1)/1_Complexity_of_object-oriented_programming_(node2)/Chapter_1/1.1.2_UML_101/1.1.2_UML_101_content.md"
}